{
    "GSW": {
        "TEAM_ID": 1610612744,
        "TEAM_NAME": "Golden State Warriors",
        "TEAM_ABBREVIATION": "GSW",
        "GP": 82,
        "G": 82,
        "FGA_FREQUENCY": 1.0,
        "FGM": 3489,
        "FGA": 6823,
        "FG_PCT": 0.511,
        "EFG_PCT": 0.59,
        "FG2A_FREQUENCY": 0.622,
        "FG2M": 2412,
        "FG2A": 4243,
        "FG2_PCT": 0.568,
        "FG3A_FREQUENCY": 0.378,
        "FG3M": 1077,
        "FG3A": 2580,
        "FG3_PCT": 0.417
    },
    "BOS": {
        "TEAM_ID": 1610612738,
        "TEAM_NAME": "Boston Celtics",
        "TEAM_ABBREVIATION": "BOS",
        "GP": 81,
        "G": 81,
        "FGA_FREQUENCY": 1.0,
        "FGM": 3176,
        "FGA": 6787,
        "FG_PCT": 0.468,
        "EFG_PCT": 0.52,
        "FG2A_FREQUENCY": 0.692,
        "FG2M": 2473,
        "FG2A": 4697,
        "FG2_PCT": 0.527,
        "FG3A_FREQUENCY": 0.308,
        "FG3M": 703,
        "FG3A": 2090,
        "FG3_PCT": 0.336
    },
    "DET": {
        "TEAM_ID": 1610612765,
        "TEAM_NAME": "Detroit Pistons",
        "TEAM_ABBREVIATION": "DET",
        "GP": 82,
        "G": 82,
        "FGA_FREQUENCY": 1.0,
        "FGM": 3111,
        "FGA": 6720,
        "FG_PCT": 0.463,
        "EFG_PCT": 0.518,
        "FG2A_FREQUENCY": 0.683,
        "FG2M": 2371,
        "FG2A": 4588,
        "FG2_PCT": 0.517,
        "FG3A_FREQUENCY": 0.317,
        "FG3M": 740,
        "FG3A": 2132,
        "FG3_PCT": 0.347
    },
    "OKC": {
        "TEAM_ID": 1610612760,
        "TEAM_NAME": "Oklahoma City Thunder",
        "TEAM_ABBREVIATION": "OKC",
        "GP": 82,
        "G": 82,
        "FGA_FREQUENCY": 1.0,
        "FGM": 3372,
        "FGA": 6709,
        "FG_PCT": 0.503,
        "EFG_PCT": 0.553,
        "FG2A_FREQUENCY": 0.711,
        "FG2M": 2694,
        "FG2A": 4771,
        "FG2_PCT": 0.565,
        "FG3A_FREQUENCY": 0.289,
        "FG3M": 678,
        "FG3A": 1938,
        "FG3_PCT": 0.35
    },
    "CHI": {
        "TEAM_ID": 1610612741,
        "TEAM_NAME": "Chicago Bulls",
        "TEAM_ABBREVIATION": "CHI",
        "GP": 82,
        "G": 82,
        "FGA_FREQUENCY": 1.0,
        "FGM": 3165,
        "FGA": 6703,
        "FG_PCT": 0.472,
        "EFG_PCT": 0.521,
        "FG2A_FREQUENCY": 0.74,
        "FG2M": 2514,
        "FG2A": 4963,
        "FG2_PCT": 0.507,
        "FG3A_FREQUENCY": 0.26,
        "FG3M": 651,
        "FG3A": 1740,
        "FG3_PCT": 0.374
    },
    "WAS": {
        "TEAM_ID": 1610612764,
        "TEAM_NAME": "Washington Wizards",
        "TEAM_ABBREVIATION": "WAS",
        "GP": 82,
        "G": 82,
        "FGA_FREQUENCY": 1.0,
        "FGM": 3238,
        "FGA": 6677,
        "FG_PCT": 0.485,
        "EFG_PCT": 0.538,
        "FG2A_FREQUENCY": 0.705,
        "FG2M": 2529,
        "FG2A": 4707,
        "FG2_PCT": 0.537,
        "FG3A_FREQUENCY": 0.295,
        "FG3M": 709,
        "FG3A": 1970,
        "FG3_PCT": 0.36
    },
    "IND": {
        "TEAM_ID": 1610612754,
        "TEAM_NAME": "Indiana Pacers",
        "TEAM_ABBREVIATION": "IND",
        "GP": 82,
        "G": 82,
        "FGA_FREQUENCY": 1.0,
        "FGM": 3141,
        "FGA": 6619,
        "FG_PCT": 0.475,
        "EFG_PCT": 0.525,
        "FG2A_FREQUENCY": 0.717,
        "FG2M": 2479,
        "FG2A": 4747,
        "FG2_PCT": 0.522,
        "FG3A_FREQUENCY": 0.283,
        "FG3M": 662,
        "FG3A": 1872,
        "FG3_PCT": 0.354
    },
    "NOP": {
        "TEAM_ID": 1610612740,
        "TEAM_NAME": "New Orleans Pelicans",
        "TEAM_ABBREVIATION": "NOP",
        "GP": 82,
        "G": 82,
        "FGA_FREQUENCY": 1.0,
        "FGM": 3153,
        "FGA": 6614,
        "FG_PCT": 0.477,
        "EFG_PCT": 0.53,
        "FG2A_FREQUENCY": 0.707,
        "FG2M": 2451,
        "FG2A": 4676,
        "FG2_PCT": 0.524,
        "FG3A_FREQUENCY": 0.293,
        "FG3M": 702,
        "FG3A": 1938,
        "FG3_PCT": 0.362
    },
    "POR": {
        "TEAM_ID": 1610612757,
        "TEAM_NAME": "Portland Trail Blazers",
        "TEAM_ABBREVIATION": "POR",
        "GP": 82,
        "G": 82,
        "FGA_FREQUENCY": 1.0,
        "FGM": 3161,
        "FGA": 6602,
        "FG_PCT": 0.479,
        "EFG_PCT": 0.544,
        "FG2A_FREQUENCY": 0.649,
        "FG2M": 2297,
        "FG2A": 4282,
        "FG2_PCT": 0.536,
        "FG3A_FREQUENCY": 0.351,
        "FG3M": 864,
        "FG3A": 2320,
        "FG3_PCT": 0.372
    },
    "ORL": {
        "TEAM_ID": 1610612753,
        "TEAM_NAME": "Orlando Magic",
        "TEAM_ABBREVIATION": "ORL",
        "GP": 81,
        "G": 81,
        "FGA_FREQUENCY": 1.0,
        "FGM": 3198,
        "FGA": 6586,
        "FG_PCT": 0.486,
        "EFG_PCT": 0.533,
        "FG2A_FREQUENCY": 0.729,
        "FG2M": 2571,
        "FG2A": 4803,
        "FG2_PCT": 0.535,
        "FG3A_FREQUENCY": 0.271,
        "FG3M": 627,
        "FG3A": 1783,
        "FG3_PCT": 0.352
    },
    "SAC": {
        "TEAM_ID": 1610612758,
        "TEAM_NAME": "Sacramento Kings",
        "TEAM_ABBREVIATION": "SAC",
        "GP": 81,
        "G": 81,
        "FGA_FREQUENCY": 1.0,
        "FGM": 3254,
        "FGA": 6574,
        "FG_PCT": 0.495,
        "EFG_PCT": 0.545,
        "FG2A_FREQUENCY": 0.725,
        "FG2M": 2601,
        "FG2A": 4766,
        "FG2_PCT": 0.546,
        "FG3A_FREQUENCY": 0.275,
        "FG3M": 653,
        "FG3A": 1808,
        "FG3_PCT": 0.361
    },
    "PHX": {
        "TEAM_ID": 1610612756,
        "TEAM_NAME": "Phoenix Suns",
        "TEAM_ABBREVIATION": "PHX",
        "GP": 82,
        "G": 82,
        "FGA_FREQUENCY": 1.0,
        "FGM": 3050,
        "FGA": 6567,
        "FG_PCT": 0.464,
        "EFG_PCT": 0.521,
        "FG2A_FREQUENCY": 0.68,
        "FG2M": 2312,
        "FG2A": 4466,
        "FG2_PCT": 0.518,
        "FG3A_FREQUENCY": 0.32,
        "FG3M": 738,
        "FG3A": 2101,
        "FG3_PCT": 0.351
    },
    "NYK": {
        "TEAM_ID": 1610612752,
        "TEAM_NAME": "New York Knicks",
        "TEAM_ABBREVIATION": "NYK",
        "GP": 82,
        "G": 82,
        "FGA_FREQUENCY": 1.0,
        "FGM": 3021,
        "FGA": 6542,
        "FG_PCT": 0.462,
        "EFG_PCT": 0.508,
        "FG2A_FREQUENCY": 0.732,
        "FG2M": 2411,
        "FG2A": 4786,
        "FG2_PCT": 0.504,
        "FG3A_FREQUENCY": 0.268,
        "FG3M": 610,
        "FG3A": 1756,
        "FG3_PCT": 0.347
    },
    "DAL": {
        "TEAM_ID": 1610612742,
        "TEAM_NAME": "Dallas Mavericks",
        "TEAM_ABBREVIATION": "DAL",
        "GP": 82,
        "G": 82,
        "FGA_FREQUENCY": 1.0,
        "FGM": 3060,
        "FGA": 6531,
        "FG_PCT": 0.469,
        "EFG_PCT": 0.53,
        "FG2A_FREQUENCY": 0.643,
        "FG2M": 2254,
        "FG2A": 4202,
        "FG2_PCT": 0.536,
        "FG3A_FREQUENCY": 0.357,
        "FG3M": 806,
        "FG3A": 2329,
        "FG3_PCT": 0.346
    },
    "CLE": {
        "TEAM_ID": 1610612739,
        "TEAM_NAME": "Cleveland Cavaliers",
        "TEAM_ABBREVIATION": "CLE",
        "GP": 82,
        "G": 82,
        "FGA_FREQUENCY": 1.0,
        "FGM": 3166,
        "FGA": 6517,
        "FG_PCT": 0.486,
        "EFG_PCT": 0.553,
        "FG2A_FREQUENCY": 0.63,
        "FG2M": 2286,
        "FG2A": 4108,
        "FG2_PCT": 0.556,
        "FG3A_FREQUENCY": 0.37,
        "FG3M": 880,
        "FG3A": 2409,
        "FG3_PCT": 0.365
    },
    "ATL": {
        "TEAM_ID": 1610612737,
        "TEAM_NAME": "Atlanta Hawks",
        "TEAM_ABBREVIATION": "ATL",
        "GP": 82,
        "G": 82,
        "FGA_FREQUENCY": 1.0,
        "FGM": 3168,
        "FGA": 6512,
        "FG_PCT": 0.486,
        "EFG_PCT": 0.549,
        "FG2A_FREQUENCY": 0.644,
        "FG2M": 2353,
        "FG2A": 4196,
        "FG2_PCT": 0.561,
        "FG3A_FREQUENCY": 0.356,
        "FG3M": 815,
        "FG3A": 2316,
        "FG3_PCT": 0.352
    },
    "LAC": {
        "TEAM_ID": 1610612746,
        "TEAM_NAME": "LA Clippers",
        "TEAM_ABBREVIATION": "LAC",
        "GP": 82,
        "G": 82,
        "FGA_FREQUENCY": 1.0,
        "FGM": 3140,
        "FGA": 6499,
        "FG_PCT": 0.483,
        "EFG_PCT": 0.544,
        "FG2A_FREQUENCY": 0.665,
        "FG2M": 2343,
        "FG2A": 4320,
        "FG2_PCT": 0.542,
        "FG3A_FREQUENCY": 0.335,
        "FG3M": 797,
        "FG3A": 2179,
        "FG3_PCT": 0.366
    },
    "LAL": {
        "TEAM_ID": 1610612747,
        "TEAM_NAME": "Los Angeles Lakers",
        "TEAM_ABBREVIATION": "LAL",
        "GP": 82,
        "G": 82,
        "FGA_FREQUENCY": 1.0,
        "FGM": 2880,
        "FGA": 6498,
        "FG_PCT": 0.443,
        "EFG_PCT": 0.492,
        "FG2A_FREQUENCY": 0.693,
        "FG2M": 2241,
        "FG2A": 4504,
        "FG2_PCT": 0.498,
        "FG3A_FREQUENCY": 0.307,
        "FG3M": 639,
        "FG3A": 1994,
        "FG3_PCT": 0.32
    },
    "BKN": {
        "TEAM_ID": 1610612751,
        "TEAM_NAME": "Brooklyn Nets",
        "TEAM_ABBREVIATION": "BKN",
        "GP": 82,
        "G": 82,
        "FGA_FREQUENCY": 1.0,
        "FGM": 3135,
        "FGA": 6489,
        "FG_PCT": 0.483,
        "EFG_PCT": 0.524,
        "FG2A_FREQUENCY": 0.769,
        "FG2M": 2604,
        "FG2A": 4993,
        "FG2_PCT": 0.522,
        "FG3A_FREQUENCY": 0.231,
        "FG3M": 531,
        "FG3A": 1496,
        "FG3_PCT": 0.355
    },
    "DEN": {
        "TEAM_ID": 1610612743,
        "TEAM_NAME": "Denver Nuggets",
        "TEAM_ABBREVIATION": "DEN",
        "GP": 82,
        "G": 82,
        "FGA_FREQUENCY": 1.0,
        "FGM": 3093,
        "FGA": 6487,
        "FG_PCT": 0.477,
        "EFG_PCT": 0.527,
        "FG2A_FREQUENCY": 0.703,
        "FG2M": 2437,
        "FG2A": 4560,
        "FG2_PCT": 0.534,
        "FG3A_FREQUENCY": 0.297,
        "FG3M": 656,
        "FG3A": 1927,
        "FG3_PCT": 0.34
    },
    "SAS": {
        "TEAM_ID": 1610612759,
        "TEAM_NAME": "San Antonio Spurs",
        "TEAM_ABBREVIATION": "SAS",
        "GP": 82,
        "G": 82,
        "FGA_FREQUENCY": 1.0,
        "FGM": 3289,
        "FGA": 6478,
        "FG_PCT": 0.508,
        "EFG_PCT": 0.552,
        "FG2A_FREQUENCY": 0.767,
        "FG2M": 2719,
        "FG2A": 4970,
        "FG2_PCT": 0.547,
        "FG3A_FREQUENCY": 0.233,
        "FG3M": 570,
        "FG3A": 1508,
        "FG3_PCT": 0.378
    },
    "CHA": {
        "TEAM_ID": 1610612766,
        "TEAM_NAME": "Charlotte Hornets",
        "TEAM_ABBREVIATION": "CHA",
        "GP": 82,
        "G": 82,
        "FGA_FREQUENCY": 1.0,
        "FGM": 3036,
        "FGA": 6474,
        "FG_PCT": 0.469,
        "EFG_PCT": 0.536,
        "FG2A_FREQUENCY": 0.63,
        "FG2M": 2163,
        "FG2A": 4079,
        "FG2_PCT": 0.53,
        "FG3A_FREQUENCY": 0.37,
        "FG3M": 873,
        "FG3A": 2395,
        "FG3_PCT": 0.365
    },
    "HOU": {
        "TEAM_ID": 1610612745,
        "TEAM_NAME": "Houston Rockets",
        "TEAM_ABBREVIATION": "HOU",
        "GP": 82,
        "G": 82,
        "FGA_FREQUENCY": 1.0,
        "FGM": 3094,
        "FGA": 6443,
        "FG_PCT": 0.48,
        "EFG_PCT": 0.548,
        "FG2A_FREQUENCY": 0.609,
        "FG2M": 2216,
        "FG2A": 3922,
        "FG2_PCT": 0.565,
        "FG3A_FREQUENCY": 0.391,
        "FG3M": 878,
        "FG3A": 2521,
        "FG3_PCT": 0.348
    },
    "PHI": {
        "TEAM_ID": 1610612755,
        "TEAM_NAME": "Philadelphia 76ers",
        "TEAM_ABBREVIATION": "PHI",
        "GP": 82,
        "G": 82,
        "FGA_FREQUENCY": 1.0,
        "FGM": 2970,
        "FGA": 6421,
        "FG_PCT": 0.463,
        "EFG_PCT": 0.522,
        "FG2A_FREQUENCY": 0.651,
        "FG2M": 2206,
        "FG2A": 4179,
        "FG2_PCT": 0.528,
        "FG3A_FREQUENCY": 0.349,
        "FG3M": 764,
        "FG3A": 2242,
        "FG3_PCT": 0.341
    },
    "MEM": {
        "TEAM_ID": 1610612763,
        "TEAM_NAME": "Memphis Grizzlies",
        "TEAM_ABBREVIATION": "MEM",
        "GP": 82,
        "G": 82,
        "FGA_FREQUENCY": 1.0,
        "FGM": 3019,
        "FGA": 6390,
        "FG_PCT": 0.472,
        "EFG_PCT": 0.512,
        "FG2A_FREQUENCY": 0.763,
        "FG2M": 2515,
        "FG2A": 4877,
        "FG2_PCT": 0.516,
        "FG3A_FREQUENCY": 0.237,
        "FG3M": 504,
        "FG3A": 1513,
        "FG3_PCT": 0.333
    },
    "MIA": {
        "TEAM_ID": 1610612748,
        "TEAM_NAME": "Miami Heat",
        "TEAM_ABBREVIATION": "MIA",
        "GP": 82,
        "G": 82,
        "FGA_FREQUENCY": 1.0,
        "FGM": 3150,
        "FGA": 6360,
        "FG_PCT": 0.495,
        "EFG_PCT": 0.534,
        "FG2A_FREQUENCY": 0.769,
        "FG2M": 2652,
        "FG2A": 4889,
        "FG2_PCT": 0.542,
        "FG3A_FREQUENCY": 0.231,
        "FG3M": 498,
        "FG3A": 1471,
        "FG3_PCT": 0.339
    },
    "MIL": {
        "TEAM_ID": 1610612749,
        "TEAM_NAME": "Milwaukee Bucks",
        "TEAM_ABBREVIATION": "MIL",
        "GP": 82,
        "G": 82,
        "FGA_FREQUENCY": 1.0,
        "FGM": 3145,
        "FGA": 6277,
        "FG_PCT": 0.501,
        "EFG_PCT": 0.536,
        "FG2A_FREQUENCY": 0.798,
        "FG2M": 2705,
        "FG2A": 5012,
        "FG2_PCT": 0.54,
        "FG3A_FREQUENCY": 0.202,
        "FG3M": 440,
        "FG3A": 1265,
        "FG3_PCT": 0.348
    },
    "MIN": {
        "TEAM_ID": 1610612750,
        "TEAM_NAME": "Minnesota Timberwolves",
        "TEAM_ABBREVIATION": "MIN",
        "GP": 82,
        "G": 82,
        "FGA_FREQUENCY": 1.0,
        "FGM": 3093,
        "FGA": 6238,
        "FG_PCT": 0.496,
        "EFG_PCT": 0.532,
        "FG2A_FREQUENCY": 0.786,
        "FG2M": 2638,
        "FG2A": 4901,
        "FG2_PCT": 0.538,
        "FG3A_FREQUENCY": 0.214,
        "FG3M": 455,
        "FG3A": 1337,
        "FG3_PCT": 0.34
    },
    "UTA": {
        "TEAM_ID": 1610612762,
        "TEAM_NAME": "Utah Jazz",
        "TEAM_ABBREVIATION": "UTA",
        "GP": 82,
        "G": 82,
        "FGA_FREQUENCY": 1.0,
        "FGM": 2957,
        "FGA": 6208,
        "FG_PCT": 0.476,
        "EFG_PCT": 0.532,
        "FG2A_FREQUENCY": 0.686,
        "FG2M": 2263,
        "FG2A": 4260,
        "FG2_PCT": 0.531,
        "FG3A_FREQUENCY": 0.314,
        "FG3M": 694,
        "FG3A": 1948,
        "FG3_PCT": 0.356
    },
    "TOR": {
        "TEAM_ID": 1610612761,
        "TEAM_NAME": "Toronto Raptors",
        "TEAM_ABBREVIATION": "TOR",
        "GP": 81,
        "G": 81,
        "FGA_FREQUENCY": 1.0,
        "FGM": 2969,
        "FGA": 6146,
        "FG_PCT": 0.483,
        "EFG_PCT": 0.54,
        "FG2A_FREQUENCY": 0.695,
        "FG2M": 2269,
        "FG2A": 4272,
        "FG2_PCT": 0.531,
        "FG3A_FREQUENCY": 0.305,
        "FG3M": 700,
        "FG3A": 1874,
        "FG3_PCT": 0.374
    }
}