[{"py/object": "src.classes.QuarterOdds.QuarterOdds", "awayPlayerFloorOdds": "-145.0261780104712", "homePlayerFloorOdds": "-134.71425006239082", "kellyBet": null, "homeTeamFirstQuarterOdds": "-112", "awayTeamFirstQuarterOdds": "-114", "home": "IND", "away": "CHI", "fetchedDatetime": "2021-04-06 09:52:38.780408", "gameDatetime": null, "exchange": "draftkings", "marketUrl": null, "isTeamOnly": false, "isPlayersOnly": false, "gameCode": "IND @ CHI 2021-04-06", "quarter": "QUARTER_1", "isFullGame": false, "homePlayerOddsList": [{"player": "Caris LeVert", "odds": "+500", "team": "IND"}, {"player": "Myles Turner", "odds": "+800", "team": "IND"}, {"player": "Justin Holiday", "odds": "+850", "team": "IND"}, {"player": "Doug McDermott", "odds": "+900", "team": "IND"}, {"player": "Edmond Sumner", "odds": "+1000", "team": "IND"}], "awayPlayerOddsList": [{"player": "Nikola Vucevic", "odds": "+500", "team": "CHI"}, {"player": "Zach LaVine", "odds": "+550", "team": "CHI"}, {"player": "Thaddeus Young", "odds": "+800", "team": "CHI"}, {"player": "Patrick Williams", "odds": "+1100", "team": "CHI"}, {"player": "Tomas Satoransky", "odds": "+1200", "team": "CHI"}], "isFirstFieldGoal": false, "bestHomeOdds": "-112", "bestAwayOdds": "-114", "minHomeWinPercentage": 0.5283018867924528, "minAwayWinPercentage": 0.5327102803738317, "expectedHomeTipper": "turnemy01.html", "expectedAwayTipper": "markkla01.html", "homeScoreProb": {"py/reduce": [{"py/function": "numpy.core.multiarray.scalar"}, {"py/tuple": [{"py/reduce": [{"py/type": "numpy.dtype"}, {"py/tuple": ["f8", false, true]}, {"py/tuple": [3, "<", null, null, null, -1, -1, 0]}]}, {"py/b64": "5Ns++PuO4D8="}]}]}, "awayScoreProb": {"py/reduce": [{"py/function": "numpy.core.multiarray.scalar"}, {"py/tuple": [{"py/id": 15}, {"py/b64": "NkiCDwji3j8="}]}]}, "homeBestKellyBet": {"py/reduce": [{"py/function": "numpy.core.multiarray.scalar"}, {"py/tuple": [{"py/id": 15}, {"py/b64": "O5YLqidkP8A="}]}]}, "awayBestKellyBet": {"py/reduce": [{"py/function": "numpy.core.multiarray.scalar"}, {"py/tuple": [{"py/id": 15}, {"py/b64": "gHSE6SBRYsA="}]}]}, "betOnHome": {"py/reduce": [{"py/function": "numpy.core.multiarray.scalar"}, {"py/tuple": [{"py/reduce": [{"py/type": "numpy.dtype"}, {"py/tuple": ["b1", false, true]}, {"py/tuple": [3, "|", null, null, null, -1, -1, 0]}]}, {"py/b64": "AA=="}]}]}, "betOnAway": {"py/id": 19}, "homeEVFactor": {"py/reduce": [{"py/function": "numpy.core.multiarray.scalar"}, {"py/tuple": [{"py/id": 15}, {"py/b64": "FNctqMpX7z8="}]}]}, "awayEVFactor": {"py/reduce": [{"py/function": "numpy.core.multiarray.scalar"}, {"py/tuple": [{"py/id": 15}, {"py/b64": "VC0wy5L87D8="}]}]}, "bestEVFactor": {"py/id": 21}, "betOnVia": "TEAM"}, {"py/object": "src.classes.QuarterOdds.QuarterOdds", "awayPlayerFloorOdds": "-143.16502683800405", "homePlayerFloorOdds": "-131.5868263473054", "kellyBet": null, "homeTeamFirstQuarterOdds": "-112", "awayTeamFirstQuarterOdds": "-112", "home": "BOS", "away": "PHI", "fetchedDatetime": "2021-04-06 09:52:38.780478", "gameDatetime": null, "exchange": "draftkings", "marketUrl": null, "isTeamOnly": false, "isPlayersOnly": false, "gameCode": "BOS @ PHI 2021-04-06", "quarter": "QUARTER_1", "isFullGame": false, "homePlayerOddsList": [{"player": "Jayson Tatum", "odds": "+550", "team": "BOS"}, {"player": "Jaylen Brown", "odds": "+600", "team": "BOS"}, {"player": "Kemba Walker", "odds": "+750", "team": "BOS"}, {"player": "Marcus Smart", "odds": "+1200", "team": "BOS"}, {"player": "Robert Williams", "odds": "+1200", "team": "BOS"}], "awayPlayerOddsList": [{"player": "Joel Embiid", "odds": "+470", "team": "PHI"}, {"player": "Tobias Harris", "odds": "+650", "team": "PHI"}, {"player": "Ben Simmons", "odds": "+750", "team": "PHI"}, {"player": "Seth Curry", "odds": "+1000", "team": "PHI"}, {"player": "Danny Green", "odds": "+1300", "team": "PHI"}], "isFirstFieldGoal": false, "bestHomeOdds": "-112", "bestAwayOdds": "-112", "minHomeWinPercentage": 0.5283018867924528, "minAwayWinPercentage": 0.5283018867924528, "expectedHomeTipper": "williro04.html", "expectedAwayTipper": "scottmi01.html", "homeScoreProb": {"py/reduce": [{"py/function": "numpy.core.multiarray.scalar"}, {"py/tuple": [{"py/id": 15}, {"py/b64": "tLzqvRZt3z8="}]}]}, "awayScoreProb": {"py/reduce": [{"py/function": "numpy.core.multiarray.scalar"}, {"py/tuple": [{"py/id": 15}, {"py/b64": "paEKoXRJ4D8="}]}]}, "homeBestKellyBet": {"py/reduce": [{"py/function": "numpy.core.multiarray.scalar"}, {"py/tuple": [{"py/id": 15}, {"py/b64": "IPTLIEX2WsA="}]}]}, "awayBestKellyBet": {"py/reduce": [{"py/function": "numpy.core.multiarray.scalar"}, {"py/tuple": [{"py/id": 15}, {"py/b64": "ZH7OJNz5S8A="}]}]}, "betOnHome": {"py/id": 19}, "betOnAway": {"py/id": 19}, "homeEVFactor": {"py/reduce": [{"py/function": "numpy.core.multiarray.scalar"}, {"py/tuple": [{"py/id": 15}, {"py/b64": "mHJQGBq+7T8="}]}]}, "awayEVFactor": {"py/reduce": [{"py/function": "numpy.core.multiarray.scalar"}, {"py/tuple": [{"py/id": 15}, {"py/b64": "itZBDC/U7j8="}]}]}, "bestEVFactor": {"py/id": 41}, "betOnVia": "TEAM"}, {"py/object": "src.classes.QuarterOdds.QuarterOdds", "awayPlayerFloorOdds": null, "homePlayerFloorOdds": null, "kellyBet": null, "homeTeamFirstQuarterOdds": "-118", "awayTeamFirstQuarterOdds": "-106", "home": "TOR", "away": "LAL", "fetchedDatetime": "2021-04-06 09:52:38.780488", "gameDatetime": null, "exchange": "draftkings", "marketUrl": null, "isTeamOnly": false, "isPlayersOnly": false, "gameCode": "TOR @ LAL 2021-04-06", "quarter": "QUARTER_1", "isFullGame": false, "homePlayerOddsList": [], "awayPlayerOddsList": [], "isFirstFieldGoal": false, "bestHomeOdds": "-118", "bestAwayOdds": "-106", "minHomeWinPercentage": 0.5412844036697247, "minAwayWinPercentage": 0.5145631067961165, "expectedHomeTipper": "bouchch01.html", "expectedAwayTipper": "gasolma01.html", "homeScoreProb": {"py/reduce": [{"py/function": "numpy.core.multiarray.scalar"}, {"py/tuple": [{"py/id": 15}, {"py/b64": "HX9k/N4S3z8="}]}]}, "awayScoreProb": {"py/reduce": [{"py/function": "numpy.core.multiarray.scalar"}, {"py/tuple": [{"py/id": 15}, {"py/b64": "csDNgZB24D8="}]}]}, "homeBestKellyBet": {"py/reduce": [{"py/function": "numpy.core.multiarray.scalar"}, {"py/tuple": [{"py/id": 15}, {"py/b64": "04Vqhl+9ZMA="}]}]}, "awayBestKellyBet": {"py/reduce": [{"py/function": "numpy.core.multiarray.scalar"}, {"py/tuple": [{"py/id": 15}, {"py/b64": "42ENrd8t0L8="}]}]}, "betOnHome": {"py/id": 19}, "betOnAway": {"py/id": 19}, "homeEVFactor": {"py/reduce": [{"py/function": "numpy.core.multiarray.scalar"}, {"py/tuple": [{"py/id": 15}, {"py/b64": "Z2gXwiS07D8="}]}]}, "awayEVFactor": {"py/reduce": [{"py/function": "numpy.core.multiarray.scalar"}, {"py/tuple": [{"py/id": 15}, {"py/b64": "1HrTlpH+7z8="}]}]}, "bestEVFactor": {"py/id": 50}, "betOnVia": "TEAM"}, {"py/object": "src.classes.QuarterOdds.QuarterOdds", "awayPlayerFloorOdds": null, "homePlayerFloorOdds": null, "kellyBet": {"bet": {"py/reduce": [{"py/function": "numpy.core.multiarray.scalar"}, {"py/tuple": [{"py/id": 15}, {"py/b64": "UbwGEIkIYkA="}]}]}, "team": "NOP"}, "homeTeamFirstQuarterOdds": "-112", "awayTeamFirstQuarterOdds": "-112", "home": "ATL", "away": "NOP", "fetchedDatetime": "2021-04-06 09:52:38.780496", "gameDatetime": null, "exchange": "draftkings", "marketUrl": null, "isTeamOnly": false, "isPlayersOnly": false, "gameCode": "ATL @ NOP 2021-04-06", "quarter": "QUARTER_1", "isFullGame": false, "homePlayerOddsList": [], "awayPlayerOddsList": [], "isFirstFieldGoal": false, "bestHomeOdds": "-112", "bestAwayOdds": "-112", "minHomeWinPercentage": 0.5283018867924528, "minAwayWinPercentage": 0.5283018867924528, "expectedHomeTipper": "capelca01.html", "expectedAwayTipper": "adamsst01.html", "homeScoreProb": {"py/reduce": [{"py/function": "numpy.core.multiarray.scalar"}, {"py/tuple": [{"py/id": 15}, {"py/b64": "ry+5kn//2j8="}]}]}, "awayScoreProb": {"py/reduce": [{"py/function": "numpy.core.multiarray.scalar"}, {"py/tuple": [{"py/id": 15}, {"py/b64": "J2ijNkCA4j8="}]}]}, "homeBestKellyBet": {"py/reduce": [{"py/function": "numpy.core.multiarray.scalar"}, {"py/tuple": [{"py/id": 15}, {"py/b64": "ACvQVBFBc8A="}]}]}, "awayBestKellyBet": {"py/id": 53}, "betOnHome": {"py/id": 19}, "betOnAway": {"py/reduce": [{"py/function": "numpy.core.multiarray.scalar"}, {"py/tuple": [{"py/id": 20}, {"py/b64": "AQ=="}]}]}, "homeEVFactor": {"py/reduce": [{"py/function": "numpy.core.multiarray.scalar"}, {"py/tuple": [{"py/id": 15}, {"py/b64": "/ENvTz2N6T8="}]}]}, "awayEVFactor": {"py/reduce": [{"py/function": "numpy.core.multiarray.scalar"}, {"py/tuple": [{"py/id": 15}, {"py/b64": "koKR6oWC8T8="}]}]}, "bestEVFactor": {"py/id": 61}, "betOnVia": "TEAM"}, {"py/object": "src.classes.QuarterOdds.QuarterOdds", "awayPlayerFloorOdds": "-113.9384116693679", "homePlayerFloorOdds": "-170.9677419354839", "kellyBet": null, "homeTeamFirstQuarterOdds": "-137", "awayTeamFirstQuarterOdds": "+108", "home": "MIA", "away": "MEM", "fetchedDatetime": "2021-04-06 09:52:38.780504", "gameDatetime": null, "exchange": "draftkings", "marketUrl": null, "isTeamOnly": false, "isPlayersOnly": false, "gameCode": "MIA @ MEM 2021-04-06", "quarter": "QUARTER_1", "isFullGame": false, "homePlayerOddsList": [{"player": "Jimmy Butler", "odds": "+500", "team": "MIA"}, {"player": "Bam Adebayo", "odds": "+600", "team": "MIA"}, {"player": "Victor Oladipo", "odds": "+700", "team": "MIA"}, {"player": "Duncan Robinson", "odds": "+700", "team": "MIA"}, {"player": "Trevor Ariza", "odds": "+1300", "team": "MIA"}], "awayPlayerOddsList": [{"player": "Jonas Valanciunas", "odds": "+650", "team": "MEM"}, {"player": "Ja Morant", "odds": "+700", "team": "MEM"}, {"player": "Dillon Brooks", "odds": "+900", "team": "MEM"}, {"player": "Grayson Allen", "odds": "+1000", "team": "MEM"}, {"player": "Kyle Anderson", "odds": "+1100", "team": "MEM"}], "isFirstFieldGoal": false, "bestHomeOdds": "-137", "bestAwayOdds": "+108", "minHomeWinPercentage": 0.5780590717299579, "minAwayWinPercentage": 0.4807692307692308, "expectedHomeTipper": "adebaba01.html", "expectedAwayTipper": "valanjo01.html", "homeScoreProb": {"py/reduce": [{"py/function": "numpy.core.multiarray.scalar"}, {"py/tuple": [{"py/id": 15}, {"py/b64": "a1E4CX7K4D8="}]}]}, "awayScoreProb": {"py/reduce": [{"py/function": "numpy.core.multiarray.scalar"}, {"py/tuple": [{"py/id": 15}, {"py/b64": "KV2P7QNr3j8="}]}]}, "homeBestKellyBet": {"py/reduce": [{"py/function": "numpy.core.multiarray.scalar"}, {"py/tuple": [{"py/id": 15}, {"py/b64": "iUNj/uuRZcA="}]}]}, "awayBestKellyBet": {"py/reduce": [{"py/function": "numpy.core.multiarray.scalar"}, {"py/tuple": [{"py/id": 15}, {"py/b64": "RyVXhyvaLMA="}]}]}, "betOnHome": {"py/id": 19}, "betOnAway": {"py/id": 19}, "homeEVFactor": {"py/reduce": [{"py/function": "numpy.core.multiarray.scalar"}, {"py/tuple": [{"py/id": 15}, {"py/b64": "hBHK9RMM7T8="}]}]}, "awayEVFactor": {"py/reduce": [{"py/function": "numpy.core.multiarray.scalar"}, {"py/tuple": [{"py/id": 15}, {"py/b64": "fPoP936i7z8="}]}]}, "bestEVFactor": {"py/id": 80}, "betOnVia": "TEAM"}, {"py/object": "src.classes.QuarterOdds.QuarterOdds", "awayPlayerFloorOdds": null, "homePlayerFloorOdds": null, "kellyBet": null, "homeTeamFirstQuarterOdds": "-155", "awayTeamFirstQuarterOdds": "+121", "home": "DEN", "away": "DET", "fetchedDatetime": "2021-04-06 09:52:38.780512", "gameDatetime": null, "exchange": "draftkings", "marketUrl": null, "isTeamOnly": false, "isPlayersOnly": false, "gameCode": "DEN @ DET 2021-04-06", "quarter": "QUARTER_1", "isFullGame": false, "homePlayerOddsList": [], "awayPlayerOddsList": [], "isFirstFieldGoal": false, "bestHomeOdds": "-155", "bestAwayOdds": "+121", "minHomeWinPercentage": 0.6078431372549019, "minAwayWinPercentage": 0.45248868778280543, "expectedHomeTipper": "jokicni01.html", "expectedAwayTipper": "plumlma01.html", "homeScoreProb": {"py/reduce": [{"py/function": "numpy.core.multiarray.scalar"}, {"py/tuple": [{"py/id": 15}, {"py/b64": "UF+eydyb4T8="}]}]}, "awayScoreProb": {"py/reduce": [{"py/function": "numpy.core.multiarray.scalar"}, {"py/tuple": [{"py/id": 15}, {"py/b64": "YkHDbEbI3D8="}]}]}, "homeBestKellyBet": {"py/reduce": [{"py/function": "numpy.core.multiarray.scalar"}, {"py/tuple": [{"py/id": 15}, {"py/b64": "kumnxQkMacA="}]}]}, "awayBestKellyBet": {"py/reduce": [{"py/function": "numpy.core.multiarray.scalar"}, {"py/tuple": [{"py/id": 15}, {"py/b64": "Iqj73oSSG8A="}]}]}, "betOnHome": {"py/id": 19}, "betOnAway": {"py/id": 19}, "homeEVFactor": {"py/reduce": [{"py/function": "numpy.core.multiarray.scalar"}, {"py/tuple": [{"py/id": 15}, {"py/b64": "lLWpKin47D8="}]}]}, "awayEVFactor": {"py/reduce": [{"py/function": "numpy.core.multiarray.scalar"}, {"py/tuple": [{"py/id": 15}, {"py/b64": "IaPSqPHN7z8="}]}]}, "bestEVFactor": {"py/id": 89}, "betOnVia": "TEAM"}, {"py/object": "src.classes.QuarterOdds.QuarterOdds", "awayPlayerFloorOdds": "-115.71338780641106", "homePlayerFloorOdds": "-160.8153078202995", "kellyBet": {"bet": {"py/reduce": [{"py/function": "numpy.core.multiarray.scalar"}, {"py/tuple": [{"py/id": 15}, {"py/b64": "F0n9VmXTZkA="}]}]}, "team": "POR"}, "homeTeamFirstQuarterOdds": "-139", "awayTeamFirstQuarterOdds": "+112", "home": "LAC", "away": "POR", "fetchedDatetime": "2021-04-06 09:52:38.780520", "gameDatetime": null, "exchange": "draftkings", "marketUrl": null, "isTeamOnly": false, "isPlayersOnly": false, "gameCode": "LAC @ POR 2021-04-06", "quarter": "QUARTER_1", "isFullGame": false, "homePlayerOddsList": [{"player": "Kawhi Leonard", "odds": "+450", "team": "LAC"}, {"player": "Paul George", "odds": "+650", "team": "LAC"}, {"player": "Reggie Jackson", "odds": "+850", "team": "LAC"}, {"player": "Marcus Morris", "odds": "+850", "team": "LAC"}, {"player": "Ivica Zubac", "odds": "+1000", "team": "LAC"}], "awayPlayerOddsList": [{"player": "Damian Lillard", "odds": "+550", "team": "POR"}, {"player": "CJ McCollum", "odds": "+700", "team": "POR"}, {"player": "Enes Kanter", "odds": "+900", "team": "POR"}, {"player": "Norman Powell", "odds": "+1000", "team": "POR"}, {"player": "Robert Covington", "odds": "+1400", "team": "POR"}], "isFirstFieldGoal": false, "bestHomeOdds": "-139", "bestAwayOdds": "+112", "minHomeWinPercentage": 0.5815899581589958, "minAwayWinPercentage": 0.4716981132075472, "expectedHomeTipper": "zubaciv01.html", "expectedAwayTipper": "nurkiju01.html", "homeScoreProb": {"py/reduce": [{"py/function": "numpy.core.multiarray.scalar"}, {"py/tuple": [{"py/id": 15}, {"py/b64": "oLHM8sJJ3T8="}]}]}, "awayScoreProb": {"py/reduce": [{"py/function": "numpy.core.multiarray.scalar"}, {"py/tuple": [{"py/id": 15}, {"py/b64": "L6eZhh5b4T8="}]}]}, "homeBestKellyBet": {"py/reduce": [{"py/function": "numpy.core.multiarray.scalar"}, {"py/tuple": [{"py/id": 15}, {"py/b64": "peRKB5FGecA="}]}]}, "awayBestKellyBet": {"py/id": 92}, "betOnHome": {"py/id": 19}, "betOnAway": {"py/id": 59}, "homeEVFactor": {"py/reduce": [{"py/function": "numpy.core.multiarray.scalar"}, {"py/tuple": [{"py/id": 15}, {"py/b64": "FlqU0uot6T8="}]}]}, "awayEVFactor": {"py/reduce": [{"py/function": "numpy.core.multiarray.scalar"}, {"py/tuple": [{"py/id": 15}, {"py/b64": "NzFb1rRl8j8="}]}]}, "bestEVFactor": {"py/id": 109}, "betOnVia": "TEAM"}, {"py/object": "src.classes.QuarterOdds.QuarterOdds", "awayPlayerFloorOdds": "-188.638985005767", "homePlayerFloorOdds": "-106.89655172413796", "kellyBet": null, "homeTeamFirstQuarterOdds": "+105", "awayTeamFirstQuarterOdds": "-134", "home": "GSW", "away": "MIL", "fetchedDatetime": "2021-04-06 09:52:38.780528", "gameDatetime": null, "exchange": "draftkings", "marketUrl": null, "isTeamOnly": false, "isPlayersOnly": false, "gameCode": "GSW @ MIL 2021-04-06", "quarter": "QUARTER_1", "isFullGame": false, "homePlayerOddsList": [{"player": "Stephen Curry", "odds": "+500", "team": "GSW"}, {"player": "Andrew Wiggins", "odds": "+800", "team": "GSW"}, {"player": "Kelly Oubre Jr.", "odds": "+900", "team": "GSW"}, {"player": "James Wiseman", "odds": "+1100", "team": "GSW"}, {"player": "Draymond Green", "odds": "+1700", "team": "GSW"}], "awayPlayerOddsList": [{"player": "Giannis Antetokounmpo", "odds": "+400", "team": "MIL"}, {"player": "Jrue Holiday", "odds": "+600", "team": "MIL"}, {"player": "Khris Middleton", "odds": "+600", "team": "MIL"}, {"player": "Donte DiVincenzo", "odds": "+1000", "team": "MIL"}, {"player": "Brook Lopez", "odds": "+1200", "team": "MIL"}], "isFirstFieldGoal": false, "bestHomeOdds": "+105", "bestAwayOdds": "-134", "minHomeWinPercentage": 0.4878048780487805, "minAwayWinPercentage": 0.5726495726495726, "expectedHomeTipper": "wisemja01.html", "expectedAwayTipper": "lopezbr01.html", "homeScoreProb": {"py/reduce": [{"py/function": "numpy.core.multiarray.scalar"}, {"py/tuple": [{"py/id": 15}, {"py/b64": "HRT5T6fP3j8="}]}]}, "awayScoreProb": {"py/reduce": [{"py/function": "numpy.core.multiarray.scalar"}, {"py/tuple": [{"py/id": 15}, {"py/b64": "8XUDWCyY4D8="}]}]}, "homeBestKellyBet": {"py/reduce": [{"py/function": "numpy.core.multiarray.scalar"}, {"py/tuple": [{"py/id": 15}, {"py/b64": "gTbgAS0BMcA="}]}]}, "awayBestKellyBet": {"py/reduce": [{"py/function": "numpy.core.multiarray.scalar"}, {"py/tuple": [{"py/id": 15}, {"py/b64": "WwXcH/GWZcA="}]}]}, "betOnHome": {"py/id": 19}, "betOnAway": {"py/id": 19}, "homeEVFactor": {"py/reduce": [{"py/function": "numpy.core.multiarray.scalar"}, {"py/tuple": [{"py/id": 15}, {"py/b64": "a4GSS9iU7z8="}]}]}, "awayEVFactor": {"py/reduce": [{"py/function": "numpy.core.multiarray.scalar"}, {"py/tuple": [{"py/id": 15}, {"py/b64": "cG4opXP67D8="}]}]}, "bestEVFactor": {"py/id": 127}, "betOnVia": "TEAM"}]