[{"py/object": "src.classes.GameOdds.GameOdds", "home": "DET", "away": "TOR", "gameDatetime": null, "exchange": "draftkings", "marketUrl": null, "fetchedDatetime": "2021-03-03 09:52:44.514541", "isTeamOnly": false, "isPlayersOnly": false, "gameCode": "DET @ TOR 2021-03-03", "homeTeamOdds": "+120", "awayTeamOdds": "-148", "homePlayerOddsList": [], "awayPlayerOddsList": [], "isFirstFieldGoal": false, "homePlayerFloorOdds": "-200", "awayPlayerFloorOdds": "-200", "bestHomeOdds": "+120", "bestAwayOdds": "-148", "betOnVia": "TEAM", "minHomeWinPercentage": 0.45454545454545453, "minAwayWinPercentage": 0.5967741935483871, "expectedHomeTipper": "robyis01.html", "expectedAwayTipper": "bouchch01.html", "homeScoreProb": {"py/reduce": [{"py/function": "numpy.core.multiarray.scalar"}, {"py/tuple": [{"py/reduce": [{"py/type": "numpy.dtype"}, {"py/tuple": ["f8", 0, 1]}, {"py/tuple": [3, "<", null, null, null, -1, -1, 0]}]}, {"py/b64": "PQHBxeAV3z8="}]}]}, "awayScoreProb": {"py/reduce": [{"py/function": "numpy.core.multiarray.scalar"}, {"py/tuple": [{"py/id": 5}, {"py/b64": "Yn8fnQ914D8="}]}]}, "homeBestKellyBet": {"py/reduce": [{"py/function": "numpy.core.multiarray.scalar"}, {"py/tuple": [{"py/id": 5}, {"py/b64": "G/0yTwsZcUA="}]}]}, "awayBestKellyBet": {"py/reduce": [{"py/function": "numpy.core.multiarray.scalar"}, {"py/tuple": [{"py/id": 5}, {"py/b64": "/b+CfOU7gcA="}]}]}, "betOnHome": {"py/reduce": [{"py/function": "numpy.core.multiarray.scalar"}, {"py/tuple": [{"py/reduce": [{"py/type": "numpy.dtype"}, {"py/tuple": ["b1", 0, 1]}, {"py/tuple": [3, "|", null, null, null, -1, -1, 0]}]}, {"py/b64": "AQ=="}]}]}, "betOnAway": {"py/reduce": [{"py/function": "numpy.core.multiarray.scalar"}, {"py/tuple": [{"py/id": 10}, {"py/b64": "AA=="}]}]}, "kellyBet": {"bet": {"py/id": 7}, "team": "DET"}, "homeTeamKellyBet": {"py/reduce": [{"py/function": "numpy.core.multiarray.scalar"}, {"py/tuple": [{"py/id": 5}, {"py/b64": "G/0yTwsZcUA="}]}]}, "awayTeamKellyBet": {"py/reduce": [{"py/function": "numpy.core.multiarray.scalar"}, {"py/tuple": [{"py/id": 5}, {"py/b64": "/b+CfOU7gcA="}]}]}, "homeEVFactor": {"py/reduce": [{"py/function": "numpy.core.multiarray.scalar"}, {"py/tuple": [{"py/id": 5}, {"py/b64": "fI2QOdUY8T8="}]}]}, "awayEVFactor": {"py/reduce": [{"py/function": "numpy.core.multiarray.scalar"}, {"py/tuple": [{"py/id": 5}, {"py/b64": "DPh5TLmT6z8="}]}]}, "bestEVFactor": {"py/id": 15}}, {"py/object": "src.classes.GameOdds.GameOdds", "home": "IND", "away": "CLE", "gameDatetime": null, "exchange": "draftkings", "marketUrl": null, "fetchedDatetime": "2021-03-03 09:52:44.514750", "isTeamOnly": false, "isPlayersOnly": false, "gameCode": "IND @ CLE 2021-03-03", "homeTeamOdds": "+100", "awayTeamOdds": "-121", "homePlayerOddsList": [{"player": "Malcolm Brogdon", "odds": "+500", "team": "IND"}, {"player": "Domantas Sabonis", "odds": "+550", "team": "IND"}, {"player": "Doug McDermott", "odds": "+900", "team": "IND"}, {"player": "Myles Turner", "odds": "+950", "team": "IND"}, {"player": "Justin Holiday", "odds": "+1000", "team": "IND"}], "awayPlayerOddsList": [{"player": "Jarrett Allen", "odds": "+550", "team": "CLE"}, {"player": "Collin Sexton", "odds": "+550", "team": "CLE"}, {"player": "Darius Garland", "odds": "+750", "team": "CLE"}, {"player": "Isaac Okoro", "odds": "+1300", "team": "CLE"}, {"player": "Dean Wade", "odds": "+1400", "team": "CLE"}], "isFirstFieldGoal": false, "homePlayerFloorOdds": "-154.23298340670505", "awayPlayerFloorOdds": "-129.06075711958937", "bestHomeOdds": "+100", "bestAwayOdds": "-121", "betOnVia": "TEAM", "minHomeWinPercentage": 0.5, "minAwayWinPercentage": 0.5475113122171946, "expectedHomeTipper": "turnemy01.html", "expectedAwayTipper": "allenja01.html", "homeScoreProb": {"py/reduce": [{"py/function": "numpy.core.multiarray.scalar"}, {"py/tuple": [{"py/id": 5}, {"py/b64": "Ls440IU02j8="}]}]}, "awayScoreProb": {"py/reduce": [{"py/function": "numpy.core.multiarray.scalar"}, {"py/tuple": [{"py/id": 5}, {"py/b64": "6ZjjF73l4j8="}]}]}, "homeBestKellyBet": {"py/reduce": [{"py/function": "numpy.core.multiarray.scalar"}, {"py/tuple": [{"py/id": 5}, {"py/b64": "oKgqmViUhsA="}]}]}, "awayBestKellyBet": {"py/reduce": [{"py/function": "numpy.core.multiarray.scalar"}, {"py/tuple": [{"py/id": 5}, {"py/b64": "gb3KKqiZc0A="}]}]}, "betOnHome": {"py/id": 11}, "betOnAway": {"py/id": 9}, "kellyBet": {"bet": {"py/id": 33}, "team": "CLE"}, "homeTeamKellyBet": {"py/reduce": [{"py/function": "numpy.core.multiarray.scalar"}, {"py/tuple": [{"py/id": 5}, {"py/b64": "oKgqmViUhsA="}]}]}, "awayTeamKellyBet": {"py/reduce": [{"py/function": "numpy.core.multiarray.scalar"}, {"py/tuple": [{"py/id": 5}, {"py/b64": "gb3KKqiZc0A="}]}]}, "homeEVFactor": {"py/reduce": [{"py/function": "numpy.core.multiarray.scalar"}, {"py/tuple": [{"py/id": 5}, {"py/b64": "Ls440IU06j8="}]}]}, "awayEVFactor": {"py/reduce": [{"py/function": "numpy.core.multiarray.scalar"}, {"py/tuple": [{"py/id": 5}, {"py/b64": "qrA6VO9B8T8="}]}]}, "bestEVFactor": {"py/id": 38}}, {"py/object": "src.classes.GameOdds.GameOdds", "home": "UTA", "away": "PHI", "gameDatetime": null, "exchange": "draftkings", "marketUrl": null, "fetchedDatetime": "2021-03-03 09:52:44.514778", "isTeamOnly": false, "isPlayersOnly": false, "gameCode": "UTA @ PHI 2021-03-03", "homeTeamOdds": "-106", "awayTeamOdds": "-115", "homePlayerOddsList": [{"player": "Rudy Gobert", "odds": "+550", "team": "UTA"}, {"player": "Donovan Mitchell", "odds": "+550", "team": "UTA"}, {"player": "Bojan Bogdanovi\u0107", "odds": "+750", "team": "UTA"}, {"player": "Mike Conley", "odds": "+800", "team": "UTA"}, {"player": "Royce O'Neale", "odds": "+1400", "team": "UTA"}], "awayPlayerOddsList": [{"player": "Joel Embiid", "odds": "+500", "team": "PHI"}, {"player": "Tobias Harris", "odds": "+650", "team": "PHI"}, {"player": "Ben Simmons", "odds": "+850", "team": "PHI"}, {"player": "Seth Curry", "odds": "+1000", "team": "PHI"}, {"player": "Danny Green", "odds": "+1200", "team": "PHI"}], "isFirstFieldGoal": false, "homePlayerFloorOdds": "-151.9635165948822", "awayPlayerFloorOdds": "-134.24433140788", "bestHomeOdds": "-106", "bestAwayOdds": "-115", "betOnVia": "TEAM", "minHomeWinPercentage": 0.5145631067961165, "minAwayWinPercentage": 0.5348837209302325, "expectedHomeTipper": "goberru01.html", "expectedAwayTipper": "embiijo01.html", "homeScoreProb": {"py/reduce": [{"py/function": "numpy.core.multiarray.scalar"}, {"py/tuple": [{"py/id": 5}, {"py/b64": "8DEQ1Fuq3z8="}]}]}, "awayScoreProb": {"py/reduce": [{"py/function": "numpy.core.multiarray.scalar"}, {"py/tuple": [{"py/id": 5}, {"py/b64": "COf3FdIq4D8="}]}]}, "homeBestKellyBet": {"py/reduce": [{"py/function": "numpy.core.multiarray.scalar"}, {"py/tuple": [{"py/id": 5}, {"py/b64": "J+FugJsuY8A="}]}]}, "awayBestKellyBet": {"py/reduce": [{"py/function": "numpy.core.multiarray.scalar"}, {"py/tuple": [{"py/id": 5}, {"py/b64": "CJuPdDWna8A="}]}]}, "betOnHome": {"py/id": 11}, "betOnAway": {"py/id": 11}, "kellyBet": null, "homeTeamKellyBet": {"py/reduce": [{"py/function": "numpy.core.multiarray.scalar"}, {"py/tuple": [{"py/id": 5}, {"py/b64": "J+FugJsuY8A="}]}]}, "awayTeamKellyBet": {"py/reduce": [{"py/function": "numpy.core.multiarray.scalar"}, {"py/tuple": [{"py/id": 5}, {"py/b64": "CJuPdDWna8A="}]}]}, "homeEVFactor": {"py/reduce": [{"py/function": "numpy.core.multiarray.scalar"}, {"py/tuple": [{"py/id": 5}, {"py/b64": "MDoe9+7E7j8="}]}]}, "awayEVFactor": {"py/reduce": [{"py/function": "numpy.core.multiarray.scalar"}, {"py/tuple": [{"py/id": 5}, {"py/b64": "MMY+jcs57j8="}]}]}, "bestEVFactor": {"py/id": 58}}, {"py/object": "src.classes.GameOdds.GameOdds", "home": "BKN", "away": "HOU", "gameDatetime": null, "exchange": "draftkings", "marketUrl": null, "fetchedDatetime": "2021-03-03 09:52:44.514797", "isTeamOnly": false, "isPlayersOnly": false, "gameCode": "BKN @ HOU 2021-03-03", "homeTeamOdds": "-162", "awayTeamOdds": "+132", "homePlayerOddsList": [{"player": "Kyrie Irving", "odds": "+470", "team": "BKN"}, {"player": "James Harden", "odds": "+500", "team": "BKN"}, {"player": "Joe Harris", "odds": "+850", "team": "BKN"}, {"player": "DeAndre Jordan", "odds": "+950", "team": "BKN"}, {"player": "Bruce Brown", "odds": "+1400", "team": "BKN"}], "awayPlayerOddsList": [{"player": "Victor Oladipo", "odds": "+550", "team": "HOU"}, {"player": "John Wall", "odds": "+550", "team": "HOU"}, {"player": "Danuel House Jr.", "odds": "+1000", "team": "HOU"}, {"player": "PJ Tucker", "odds": "+1200", "team": "HOU"}, {"player": "Justin Patton", "odds": "+1200", "team": "HOU"}], "isFirstFieldGoal": false, "homePlayerFloorOdds": "-155.93329057087874", "awayPlayerFloorOdds": "-123.4375", "bestHomeOdds": "-155.93329057087874", "bestAwayOdds": "+132", "betOnVia": "TEAM", "minHomeWinPercentage": 0.6092731829573934, "minAwayWinPercentage": 0.43103448275862066, "expectedHomeTipper": "greenje02.html", "expectedAwayTipper": "tuckepj01.html", "homeScoreProb": {"py/reduce": [{"py/function": "numpy.core.multiarray.scalar"}, {"py/tuple": [{"py/id": 5}, {"py/b64": "QmbkPpkk3D8="}]}]}, "awayScoreProb": {"py/reduce": [{"py/function": "numpy.core.multiarray.scalar"}, {"py/tuple": [{"py/id": 5}, {"py/b64": "38yNYLPt4T8="}]}]}, "homeBestKellyBet": {"py/reduce": [{"py/function": "numpy.core.multiarray.scalar"}, {"py/tuple": [{"py/id": 5}, {"py/b64": "iIqp3BtZkcA="}]}]}, "awayBestKellyBet": {"py/reduce": [{"py/function": "numpy.core.multiarray.scalar"}, {"py/tuple": [{"py/id": 5}, {"py/b64": "gFO3qxaxkkA="}]}]}, "betOnHome": {"py/id": 11}, "betOnAway": {"py/id": 9}, "kellyBet": {"bet": {"py/id": 76}, "team": "HOU"}, "homeTeamKellyBet": {"py/reduce": [{"py/function": "numpy.core.multiarray.scalar"}, {"py/tuple": [{"py/id": 5}, {"py/b64": "2BZ//6cBksA="}]}]}, "awayTeamKellyBet": {"py/reduce": [{"py/function": "numpy.core.multiarray.scalar"}, {"py/tuple": [{"py/id": 5}, {"py/b64": "gFO3qxaxkkA="}]}]}, "homeEVFactor": {"py/reduce": [{"py/function": "numpy.core.multiarray.scalar"}, {"py/tuple": [{"py/id": 5}, {"py/b64": "wsumEnQY5z8="}]}]}, "awayEVFactor": {"py/reduce": [{"py/function": "numpy.core.multiarray.scalar"}, {"py/tuple": [{"py/id": 5}, {"py/b64": "QYd7hA3M9D8="}]}]}, "bestEVFactor": {"py/id": 81}}, {"py/object": "src.classes.GameOdds.GameOdds", "home": "CHI", "away": "NOP", "gameDatetime": null, "exchange": "draftkings", "marketUrl": null, "fetchedDatetime": "2021-03-03 09:52:44.514831", "isTeamOnly": false, "isPlayersOnly": false, "gameCode": "CHI @ NOP 2021-03-03", "homeTeamOdds": "+103", "awayTeamOdds": "-125", "homePlayerOddsList": [{"player": "Zach LaVine", "odds": "+410", "team": "CHI"}, {"player": "Coby White", "odds": "+800", "team": "CHI"}, {"player": "Wendell Carter Jr.", "odds": "+950", "team": "CHI"}, {"player": "Patrick Williams", "odds": "+1100", "team": "CHI"}, {"player": "Garrett Temple", "odds": "+1200", "team": "CHI"}], "awayPlayerOddsList": [{"player": "Brandon Ingram", "odds": "+550", "team": "NOP"}, {"player": "Zion Williamson", "odds": "+600", "team": "NOP"}, {"player": "Steven Adams", "odds": "+850", "team": "NOP"}, {"player": "Eric Bledsoe", "odds": "+950", "team": "NOP"}, {"player": "Lonzo Ball", "odds": "+1000", "team": "NOP"}], "isFirstFieldGoal": false, "homePlayerFloorOdds": "-128.6676247177171", "awayPlayerFloorOdds": "-142.7854133866644", "bestHomeOdds": "+103", "bestAwayOdds": "-125", "betOnVia": "TEAM", "minHomeWinPercentage": 0.49261083743842365, "minAwayWinPercentage": 0.5555555555555556, "expectedHomeTipper": "cartewe01.html", "expectedAwayTipper": "adamsst01.html", "homeScoreProb": {"py/reduce": [{"py/function": "numpy.core.multiarray.scalar"}, {"py/tuple": [{"py/id": 5}, {"py/b64": "Thv3f/U/2z8="}]}]}, "awayScoreProb": {"py/reduce": [{"py/function": "numpy.core.multiarray.scalar"}, {"py/tuple": [{"py/id": 5}, {"py/b64": "WXIEQAVg4j8="}]}]}, "homeBestKellyBet": {"py/reduce": [{"py/function": "numpy.core.multiarray.scalar"}, {"py/tuple": [{"py/id": 5}, {"py/b64": "+fiXII/qgMA="}]}]}, "awayBestKellyBet": {"py/reduce": [{"py/function": "numpy.core.multiarray.scalar"}, {"py/tuple": [{"py/id": 5}, {"py/b64": "/b/8SdPBYEA="}]}]}, "betOnHome": {"py/id": 11}, "betOnAway": {"py/id": 9}, "kellyBet": {"bet": {"py/id": 98}, "team": "NOP"}, "homeTeamKellyBet": {"py/reduce": [{"py/function": "numpy.core.multiarray.scalar"}, {"py/tuple": [{"py/id": 5}, {"py/b64": "+fiXII/qgMA="}]}]}, "awayTeamKellyBet": {"py/reduce": [{"py/function": "numpy.core.multiarray.scalar"}, {"py/tuple": [{"py/id": 5}, {"py/b64": "/b/8SdPBYEA="}]}]}, "homeEVFactor": {"py/reduce": [{"py/function": "numpy.core.multiarray.scalar"}, {"py/tuple": [{"py/id": 5}, {"py/b64": "EkuvLpmo6z8="}]}]}, "awayEVFactor": {"py/reduce": [{"py/function": "numpy.core.multiarray.scalar"}, {"py/tuple": [{"py/id": 5}, {"py/b64": "tjM3U56J8D8="}]}]}, "bestEVFactor": {"py/id": 103}}, {"py/object": "src.classes.GameOdds.GameOdds", "home": "ATL", "away": "ORL", "gameDatetime": null, "exchange": "draftkings", "marketUrl": null, "fetchedDatetime": "2021-03-03 09:52:44.514861", "isTeamOnly": false, "isPlayersOnly": false, "gameCode": "ATL @ ORL 2021-03-03", "homeTeamOdds": "-107", "awayTeamOdds": "-114", "homePlayerOddsList": [], "awayPlayerOddsList": [], "isFirstFieldGoal": false, "homePlayerFloorOdds": "-200", "awayPlayerFloorOdds": "-200", "bestHomeOdds": "-107", "bestAwayOdds": "-114", "betOnVia": "TEAM", "minHomeWinPercentage": 0.5169082125603864, "minAwayWinPercentage": 0.5327102803738317, "expectedHomeTipper": "capelca01.html", "expectedAwayTipper": "vucevni01.html", "homeScoreProb": {"py/reduce": [{"py/function": "numpy.core.multiarray.scalar"}, {"py/tuple": [{"py/id": 5}, {"py/b64": "p4RynW9g4j8="}]}]}, "awayScoreProb": {"py/reduce": [{"py/function": "numpy.core.multiarray.scalar"}, {"py/tuple": [{"py/id": 5}, {"py/b64": "svYaxSA/2z8="}]}]}, "homeBestKellyBet": {"py/reduce": [{"py/function": "numpy.core.multiarray.scalar"}, {"py/tuple": [{"py/id": 5}, {"py/b64": "Z1n+xqCse0A="}]}]}, "awayBestKellyBet": {"py/reduce": [{"py/function": "numpy.core.multiarray.scalar"}, {"py/tuple": [{"py/id": 5}, {"py/b64": "RSMkZ2AKicA="}]}]}, "betOnHome": {"py/id": 9}, "betOnAway": {"py/id": 11}, "kellyBet": {"bet": {"py/id": 109}, "team": "ATL"}, "homeTeamKellyBet": {"py/reduce": [{"py/function": "numpy.core.multiarray.scalar"}, {"py/tuple": [{"py/id": 5}, {"py/b64": "Z1n+xqCse0A="}]}]}, "awayTeamKellyBet": {"py/reduce": [{"py/function": "numpy.core.multiarray.scalar"}, {"py/tuple": [{"py/id": 5}, {"py/b64": "RSMkZ2AKicA="}]}]}, "homeEVFactor": {"py/reduce": [{"py/function": "numpy.core.multiarray.scalar"}, {"py/tuple": [{"py/id": 5}, {"py/b64": "sAibdY3G8T8="}]}]}, "awayEVFactor": {"py/reduce": [{"py/function": "numpy.core.multiarray.scalar"}, {"py/tuple": [{"py/id": 5}, {"py/b64": "tpYJp9SS6T8="}]}]}, "bestEVFactor": {"py/id": 114}}, {"py/object": "src.classes.GameOdds.GameOdds", "home": "CHA", "away": "MIN", "gameDatetime": null, "exchange": "draftkings", "marketUrl": null, "fetchedDatetime": "2021-03-03 09:52:44.514893", "isTeamOnly": false, "isPlayersOnly": false, "gameCode": "CHA @ MIN 2021-03-03", "homeTeamOdds": "-110", "awayTeamOdds": "-110", "homePlayerOddsList": [{"player": "Terry Rozier", "odds": "+470", "team": "CHA"}, {"player": "LaMelo Ball", "odds": "+500", "team": "CHA"}, {"player": "PJ Washington", "odds": "+1000", "team": "CHA"}, {"player": "Bismack Biyombo", "odds": "+1200", "team": "CHA"}, {"player": "Cody Martin", "odds": "+1200", "team": "CHA"}], "awayPlayerOddsList": [{"player": "Karl-Anthony Towns", "odds": "+460", "team": "MIN"}, {"player": "Anthony Edwards", "odds": "+650", "team": "MIN"}, {"player": "Josh Okogie", "odds": "+1000", "team": "MIN"}, {"player": "Ricky Rubio", "odds": "+1000", "team": "MIN"}, {"player": "Jarred Vanderbilt", "odds": "+1000", "team": "MIN"}], "isFirstFieldGoal": false, "homePlayerFloorOdds": "-142.04899777282847", "awayPlayerFloorOdds": "-140.75039082855656", "bestHomeOdds": "-110", "bestAwayOdds": "-110", "betOnVia": "TEAM", "minHomeWinPercentage": 0.5238095238095238, "minAwayWinPercentage": 0.5238095238095238, "expectedHomeTipper": "zelleco01.html", "expectedAwayTipper": "townska01.html", "homeScoreProb": {"py/reduce": [{"py/function": "numpy.core.multiarray.scalar"}, {"py/tuple": [{"py/id": 5}, {"py/b64": "383QBq932j8="}]}]}, "awayScoreProb": {"py/reduce": [{"py/function": "numpy.core.multiarray.scalar"}, {"py/tuple": [{"py/id": 5}, {"py/b64": "EZmXfCjE4j8="}]}]}, "homeBestKellyBet": {"py/reduce": [{"py/function": "numpy.core.multiarray.scalar"}, {"py/tuple": [{"py/id": 5}, {"py/b64": "j1WJK7c+isA="}]}]}, "awayBestKellyBet": {"py/reduce": [{"py/function": "numpy.core.multiarray.scalar"}, {"py/tuple": [{"py/id": 5}, {"py/b64": "lnxYbsvRfUA="}]}]}, "betOnHome": {"py/id": 11}, "betOnAway": {"py/id": 9}, "kellyBet": {"bet": {"py/id": 132}, "team": "MIN"}, "homeTeamKellyBet": {"py/reduce": [{"py/function": "numpy.core.multiarray.scalar"}, {"py/tuple": [{"py/id": 5}, {"py/b64": "j1WJK7c+isA="}]}]}, "awayTeamKellyBet": {"py/reduce": [{"py/function": "numpy.core.multiarray.scalar"}, {"py/tuple": [{"py/id": 5}, {"py/b64": "lnxYbsvRfUA="}]}]}, "homeEVFactor": {"py/reduce": [{"py/function": "numpy.core.multiarray.scalar"}, {"py/tuple": [{"py/id": 5}, {"py/b64": "miENtbJD6T8="}]}]}, "awayEVFactor": {"py/reduce": [{"py/function": "numpy.core.multiarray.scalar"}, {"py/tuple": [{"py/id": 5}, {"py/b64": "vp0zjsnp8T8="}]}]}, "bestEVFactor": {"py/id": 137}}, {"py/object": "src.classes.GameOdds.GameOdds", "home": "OKC", "away": "DAL", "gameDatetime": null, "exchange": "draftkings", "marketUrl": null, "fetchedDatetime": "2021-03-03 09:52:44.514922", "isTeamOnly": false, "isPlayersOnly": false, "gameCode": "OKC @ DAL 2021-03-03", "homeTeamOdds": "-104", "awayTeamOdds": "-118", "homePlayerOddsList": [], "awayPlayerOddsList": [], "isFirstFieldGoal": false, "homePlayerFloorOdds": "-200", "awayPlayerFloorOdds": "-200", "bestHomeOdds": "-104", "bestAwayOdds": "-118", "betOnVia": "TEAM", "minHomeWinPercentage": 0.5098039215686274, "minAwayWinPercentage": 0.5412844036697247, "expectedHomeTipper": "horfoal01.html", "expectedAwayTipper": "porzikr01.html", "homeScoreProb": {"py/reduce": [{"py/function": "numpy.core.multiarray.scalar"}, {"py/tuple": [{"py/id": 5}, {"py/b64": "QOG/Vg2O3z8="}]}]}, "awayScoreProb": {"py/reduce": [{"py/function": "numpy.core.multiarray.scalar"}, {"py/tuple": [{"py/id": 5}, {"py/b64": "YA+gVPk44D8="}]}]}, "homeBestKellyBet": {"py/reduce": [{"py/function": "numpy.core.multiarray.scalar"}, {"py/tuple": [{"py/id": 5}, {"py/b64": "IjHQQDdlYMA="}]}]}, "awayBestKellyBet": {"py/reduce": [{"py/function": "numpy.core.multiarray.scalar"}, {"py/tuple": [{"py/id": 5}, {"py/b64": "cIcI28ahb8A="}]}]}, "betOnHome": {"py/id": 11}, "betOnAway": {"py/id": 11}, "kellyBet": null, "homeTeamKellyBet": {"py/reduce": [{"py/function": "numpy.core.multiarray.scalar"}, {"py/tuple": [{"py/id": 5}, {"py/b64": "IjHQQDdlYMA="}]}]}, "awayTeamKellyBet": {"py/reduce": [{"py/function": "numpy.core.multiarray.scalar"}, {"py/tuple": [{"py/id": 5}, {"py/b64": "cIcI28ahb8A="}]}]}, "homeEVFactor": {"py/reduce": [{"py/function": "numpy.core.multiarray.scalar"}, {"py/tuple": [{"py/id": 5}, {"py/b64": "ifWKd7Ty7j8="}]}]}, "awayEVFactor": {"py/reduce": [{"py/function": "numpy.core.multiarray.scalar"}, {"py/tuple": [{"py/id": 5}, {"py/b64": "SsFOgnH47T8="}]}]}, "bestEVFactor": {"py/id": 147}}, {"py/object": "src.classes.GameOdds.GameOdds", "home": "LAL", "away": "SAC", "gameDatetime": null, "exchange": "draftkings", "marketUrl": null, "fetchedDatetime": "2021-03-03 09:52:44.514954", "isTeamOnly": false, "isPlayersOnly": false, "gameCode": "LAL @ SAC 2021-03-03", "homeTeamOdds": "-110", "awayTeamOdds": "-110", "homePlayerOddsList": [], "awayPlayerOddsList": [], "isFirstFieldGoal": false, "homePlayerFloorOdds": "-200", "awayPlayerFloorOdds": "-200", "bestHomeOdds": "-110", "bestAwayOdds": "-110", "betOnVia": "TEAM", "minHomeWinPercentage": 0.5238095238095238, "minAwayWinPercentage": 0.5238095238095238, "expectedHomeTipper": "gasolma01.html", "expectedAwayTipper": "holmeri01.html", "homeScoreProb": {"py/reduce": [{"py/function": "numpy.core.multiarray.scalar"}, {"py/tuple": [{"py/id": 5}, {"py/b64": "fvBKVDYs4D8="}]}]}, "awayScoreProb": {"py/reduce": [{"py/function": "numpy.core.multiarray.scalar"}, {"py/tuple": [{"py/id": 5}, {"py/b64": "BB9qV5On3z8="}]}]}, "homeBestKellyBet": {"py/reduce": [{"py/function": "numpy.core.multiarray.scalar"}, {"py/tuple": [{"py/id": 5}, {"py/b64": "RkXfVxqIYcA="}]}]}, "awayBestKellyBet": {"py/reduce": [{"py/function": "numpy.core.multiarray.scalar"}, {"py/tuple": [{"py/id": 5}, {"py/b64": "3ReVeSvPa8A="}]}]}, "betOnHome": {"py/id": 11}, "betOnAway": {"py/id": 11}, "kellyBet": null, "homeTeamKellyBet": {"py/reduce": [{"py/function": "numpy.core.multiarray.scalar"}, {"py/tuple": [{"py/id": 5}, {"py/b64": "RkXfVxqIYcA="}]}]}, "awayTeamKellyBet": {"py/reduce": [{"py/function": "numpy.core.multiarray.scalar"}, {"py/tuple": [{"py/id": 5}, {"py/b64": "3ReVeSvPa8A="}]}]}, "homeEVFactor": {"py/reduce": [{"py/function": "numpy.core.multiarray.scalar"}, {"py/tuple": [{"py/id": 5}, {"py/b64": "NijsoArg7j8="}]}]}, "awayEVFactor": {"py/reduce": [{"py/function": "numpy.core.multiarray.scalar"}, {"py/tuple": [{"py/id": 5}, {"py/b64": "4DSIMDs37j8="}]}]}, "bestEVFactor": {"py/id": 158}}, {"py/object": "src.classes.GameOdds.GameOdds", "home": "GSW", "away": "POR", "gameDatetime": null, "exchange": "draftkings", "marketUrl": null, "fetchedDatetime": "2021-03-03 09:52:44.514986", "isTeamOnly": false, "isPlayersOnly": false, "gameCode": "GSW @ POR 2021-03-03", "homeTeamOdds": "-121", "awayTeamOdds": "+100", "homePlayerOddsList": [{"player": "Stephen Curry", "odds": "+550", "team": "GSW"}, {"player": "Kelly Oubre Jr.", "odds": "+850", "team": "GSW"}, {"player": "Andrew Wiggins", "odds": "+850", "team": "GSW"}, {"player": "Kevon Looney", "odds": "+1500", "team": "GSW"}, {"player": "Draymond Green", "odds": "+1700", "team": "GSW"}], "awayPlayerOddsList": [{"player": "Damian Lillard", "odds": "+380", "team": "POR"}, {"player": "Enes Kanter", "odds": "+480", "team": "POR"}, {"player": "Gary Trent Jr.", "odds": "+650", "team": "POR"}, {"player": "Robert Covington", "odds": "+1100", "team": "POR"}, {"player": "Derrick Jones Jr.", "odds": "+1300", "team": "POR"}], "isFirstFieldGoal": false, "homePlayerFloorOdds": "+107.28480680692348", "awayPlayerFloorOdds": "-201.97099293417628", "bestHomeOdds": "+107.28480680692348", "bestAwayOdds": "+100", "betOnVia": "PLAYERS", "minHomeWinPercentage": 0.48242802519118305, "minAwayWinPercentage": 0.5, "expectedHomeTipper": "looneke01.html", "expectedAwayTipper": "kanteen01.html", "homeScoreProb": {"py/reduce": [{"py/function": "numpy.core.multiarray.scalar"}, {"py/tuple": [{"py/id": 5}, {"py/b64": "dcRPX7Ws4T8="}]}]}, "awayScoreProb": {"py/reduce": [{"py/function": "numpy.core.multiarray.scalar"}, {"py/tuple": [{"py/id": 5}, {"py/b64": "FndgQZWm3D8="}]}]}, "homeBestKellyBet": {"py/reduce": [{"py/function": "numpy.core.multiarray.scalar"}, {"py/tuple": [{"py/id": 5}, {"py/b64": "qC3qqEERgkA="}]}]}, "awayBestKellyBet": {"py/reduce": [{"py/function": "numpy.core.multiarray.scalar"}, {"py/tuple": [{"py/id": 5}, {"py/b64": "9z+F29IZesA="}]}]}, "betOnHome": {"py/id": 9}, "betOnAway": {"py/id": 11}, "kellyBet": {"bet": {"py/id": 175}, "team": "GSW"}, "homeTeamKellyBet": {"py/reduce": [{"py/function": "numpy.core.multiarray.scalar"}, {"py/tuple": [{"py/id": 5}, {"py/b64": "6YI7TEqRQUA="}]}]}, "awayTeamKellyBet": {"py/reduce": [{"py/function": "numpy.core.multiarray.scalar"}, {"py/tuple": [{"py/id": 5}, {"py/b64": "9z+F29IZesA="}]}]}, "homeEVFactor": {"py/reduce": [{"py/function": "numpy.core.multiarray.scalar"}, {"py/tuple": [{"py/id": 5}, {"py/b64": "4+lNQYRR8j8="}]}]}, "awayEVFactor": {"py/reduce": [{"py/function": "numpy.core.multiarray.scalar"}, {"py/tuple": [{"py/id": 5}, {"py/b64": "FndgQZWm7D8="}]}]}, "bestEVFactor": {"py/id": 180}}]